hidt/__init__.py
hidt/evaluation.py
hidt/load_hic_format.py
hidt/loss.py
hidt/model.py
hidt/pretrained_model.pth
hidt/utils.py
hidt-0.1.2.data/scripts/HiDT
hidt-0.1.2.dist-info/LICENSE
hidt-0.1.2.dist-info/METADATA
hidt-0.1.2.dist-info/WHEEL
hidt-0.1.2.dist-info/top_level.txt
hidt-0.1.2.dist-info/RECORD
