Metadata-Version: 2.1
Name: hidt
Version: 0.1.2
Summary: A computational pipeline for identifying differential TADs from 3D genome contact maps
Home-page: https://github.com/GaoLabXDU/HiDT
Author: Li Junping
Author-email: lijunping02@qq.com
License: MIT Licence
Keywords: 3D genome,Comparative analysis,Topologically associating domains
Platform: any
License-File: LICENSE
Requires-Dist: numpy
Requires-Dist: pandas
Requires-Dist: scikit-learn
Requires-Dist: hic-straw ==1.3.1
